setup.py
pyLinguist/Prediction.py
pyLinguist/Translate.py
pyLinguist/Vocabulary.py
pyLinguist/__init__.py
pyLinguist/exc.py
pyLinguist/mixins.py
pyLinguist/utils.py
pyLinguist.egg-info/PKG-INFO
pyLinguist.egg-info/SOURCES.txt
pyLinguist.egg-info/dependency_links.txt
pyLinguist.egg-info/top_level.txt