Metadata-Version: 1.2
Name: pyLinguist
Version: 0.1.3
Summary: Yandex Linguistics APIs for Python 3.3+
Home-page: https://github.com/hell03end/pyYandexLinguistics
Author: hell03end
Author-email: hell03end@outlook.com
License: MIT License
Keywords: translate dictionary predict predictor yandex linguistics yandex-translate yandex-dictionary yandex-predictor spellerspelling grammar yandex-speller
Platform: All
Classifier: Intended Audience :: Developers
Classifier: Development Status :: 5 - Production/Stable
Classifier: License :: OSI Approved :: MIT License
Classifier: Operating System :: OS Independent
Classifier: Programming Language :: Python
Classifier: Programming Language :: Python :: 3
Classifier: Programming Language :: Python :: 3.6
Classifier: Programming Language :: Python :: 3.5
Classifier: Programming Language :: Python :: 3.4
Classifier: Programming Language :: Python :: 3.3
Classifier: Topic :: Software Development :: Libraries :: Python Modules
Requires-Python: >=3.3
